alias_free_torch/__init__.py
alias_free_torch/act.py
alias_free_torch/filter.py
alias_free_torch/resample.py
alias_free_torch-0.0.5.dist-info/LICENSE
alias_free_torch-0.0.5.dist-info/METADATA
alias_free_torch-0.0.5.dist-info/WHEEL
alias_free_torch-0.0.5.dist-info/top_level.txt
alias_free_torch-0.0.5.dist-info/RECORD
