Metadata-Version: 2.1
Name: alias-free-torch
Version: 0.0.5
Summary: alias free torch
Home-page: https://github.com/junjun3518/alias-free-torch
Author: junjun3518
Author-email: junjun3518@gmail.com
License: UNKNOWN
Keywords: alias,torch,pytorch,filter
Platform: UNKNOWN
Classifier: Programming Language :: Python :: 3
Classifier: Programming Language :: Python :: 3.5
Classifier: Programming Language :: Python :: 3.6
Classifier: Programming Language :: Python :: 3.7
Classifier: Programming Language :: Python :: 3.8
Classifier: Programming Language :: Python :: 3.9
Requires-Python: >=3
